<?xml version="1.0" encoding="UTF-8"?>
<jcr:root xmlns:cq="http://www.day.com/jcr/cq/1.0" xmlns:jcr="http://www.jcp.org/jcr/1.0" xmlns:mix="http://www.jcp.org/jcr/mix/1.0" xmlns:nt="http://www.jcp.org/jcr/nt/1.0"
    jcr:primaryType="cq:Page">
    <jcr:content
        cq:lastModified="{Date}2014-08-28T14:13:05.733-04:00"
        cq:lastModifiedBy="mage"
        cq:lastReplicated="{Date}2014-08-28T14:15:21.287-04:00"
        cq:lastReplicatedBy="mage"
        cq:lastReplicationAction="Activate"
        jcr:isCheckedOut="{Boolean}true"
        jcr:mixinTypes="[mix:versionable]"
        jcr:primaryType="cq:PageContent"
        jcr:uuid="ed4b3242-fe00-4ed8-aa94-17d41e248abf"
        hideInNav="true"
        showCurrent="{Boolean}true">
        <image
            jcr:lastModified="{Date}2014-08-28T14:13:05.729-04:00"
            jcr:lastModifiedBy="mage"
            jcr:primaryType="nt:unstructured"
            imageRotate="0"/>
    </jcr:content>
    <humble_girl_scouts_p/>
    <i_can_t_wait_to_be_a/>
    <girl_scouts_kicks_of/>
    <girl_scouts_kicks_of_0/>
    <s_mores_recipes_evol/>
    <lufkin_middle_school/>
    <gssjc_announces_sept/>
    <port_arthur_voluntee/>
</jcr:root>
